{
  "modules": {
    "A": {
      "id": "A",
      "name": "内容选题",
      "status": "idle",
      "started_at": null,
      "completed_at": null,
      "error_message": null,
      "output_file": "module_outputs/A_output.json",
      "last_input": null
    },
    "B": {
      "id": "B",
      "name": "文案创作",
      "status": "idle",
      "started_at": null,
      "completed_at": null,
      "error_message": null,
      "output_file": "module_outputs/B_output.json",
      "last_input": null
    },
    "C": {
      "id": "C",
      "name": "合规审查",
      "status": "idle",
      "started_at": null,
      "completed_at": null,
      "error_message": null,
      "output_file": "module_outputs/C_output.json",
      "last_input": null
    },
    "D": {
      "id": "D",
      "name": "视频生成",
      "status": "idle",
      "started_at": null,
      "completed_at": null,
      "error_message": null,
      "output_file": "module_outputs/D_output.json",
      "last_input": null
    },
    "E": {
      "id": "E",
      "name": "语音合成",
      "status": "idle",
      "started_at": null,
      "completed_at": null,
      "error_message": null,
      "output_file": "module_outputs/E_output.json",
      "last_input": null
    },
    "F": {
      "id": "F",
      "name": "内容组装",
      "status": "idle",
      "started_at": null,
      "completed_at": null,
      "error_message": null,
      "output_file": "module_outputs/F_output.json",
      "last_input": null
    },
    "G": {
      "id": "G",
      "name": "多平台发布",
      "status": "idle",
      "started_at": null,
      "completed_at": null,
      "error_message": null,
      "output_file": "module_outputs/G_output.json",
      "last_input": null
    }
  },
  "current_module": null,
  "workflow_started_at": null,
  "workflow_completed_at": null,
  "logs": []
}